README.rst
setup.py
lsru/__init__.py
lsru/utils.py
lsru.egg-info/PKG-INFO
lsru.egg-info/SOURCES.txt
lsru.egg-info/dependency_links.txt
lsru.egg-info/requires.txt
lsru.egg-info/top_level.txt