Metadata-Version: 2.1
Name: lsru
Version: 0.4.3
Summary: Access the ESPA API for Landsat surface reflectance data ordering and download
Home-page: https://github.com/loicdtx/landsat-espa-util
Author: Loic Dutrieux
Author-email: loic.dutrieux@gmail.com
License: GPLv3
Keywords: landsat,API,espa,usgs
Platform: UNKNOWN
Classifier: Programming Language :: Python :: 2.7
Classifier: Programming Language :: Python :: 3.3
Classifier: Programming Language :: Python :: 3.4
Classifier: Programming Language :: Python :: 3.5
Classifier: Programming Language :: Python :: 3.6
Classifier: Programming Language :: Python :: 3.7
Provides-Extra: docs
